countable_field/__init__.py
countable_field/widgets.py
countable_field/__pycache__/__init__.cpython-35.pyc
countable_field/__pycache__/widgets.cpython-35.pyc
countable_field/static/countable_field/css/styles.css
countable_field/static/countable_field/js/scripts.js
django_countable_field-1.3.dist-info/METADATA
django_countable_field-1.3.dist-info/RECORD
django_countable_field-1.3.dist-info/WHEEL
django_countable_field-1.3.dist-info/top_level.txt
example_project/__init__.py
example_project/forms.py
example_project/settings.py
example_project/urls.py
example_project/views.py
example_project/wsgi.py
tests/__init__.py
tests/test_settings.py
tests/tests.py
